mcp_python/__init__.py
mcp_python/__main__.py
mcp_python/server.py
iflow_mcp_mcp_python-0.1.3.dist-info/METADATA
iflow_mcp_mcp_python-0.1.3.dist-info/WHEEL
iflow_mcp_mcp_python-0.1.3.dist-info/entry_points.txt
iflow_mcp_mcp_python-0.1.3.dist-info/licenses/LICENSE
iflow_mcp_mcp_python-0.1.3.dist-info/RECORD
