Metadata-Version: 2.4
Name: iflow-mcp_mcp-python
Version: 0.1.3
Summary: MCP server providing a Python REPL with persistent session
Project-URL: Homepage, https://hdr.is
Project-URL: Repository, https://github.com/hdresearch/mcp-python.git
Project-URL: Issues, https://github.com/hdresearch/mcp-python/issues
Project-URL: Github, https://github.com/hdresearch/mcp-python
Author-email: Tynan Daly <tynan@hdr.is>
License-Expression: MIT
License-File: LICENSE
Keywords: mcp,python,repl,server
Classifier: Development Status :: 4 - Beta
Classifier: License :: OSI Approved :: MIT License
Classifier: Operating System :: OS Independent
Classifier: Programming Language :: Python :: 3
Classifier: Programming Language :: Python :: 3.10
Requires-Python: >=3.10
Requires-Dist: mcp
